LICENSE
MANIFEST.in
README.md
package.json
setup.py
dash_react_datepicker/DashReactDatepicker.py
dash_react_datepicker/__init__.py
dash_react_datepicker/_imports_.py
dash_react_datepicker/dash_react_datepicker.min.js
dash_react_datepicker/dash_react_datepicker.min.js.map
dash_react_datepicker/metadata.json
dash_react_datepicker/package-info.json
dash_react_datepicker.egg-info/PKG-INFO
dash_react_datepicker.egg-info/SOURCES.txt
dash_react_datepicker.egg-info/dependency_links.txt
dash_react_datepicker.egg-info/top_level.txt